pytest_spec/__init__.py
pytest_spec/patch.py
pytest_spec/plugin.py
pytest_spec/replacer.py
pytest_spec-5.2.0.dist-info/licenses/LICENSE.txt
pytest_spec-5.2.0.dist-info/METADATA
pytest_spec-5.2.0.dist-info/WHEEL
pytest_spec-5.2.0.dist-info/entry_points.txt
pytest_spec-5.2.0.dist-info/top_level.txt
pytest_spec-5.2.0.dist-info/RECORD
