Metadata-Version: 2.4
Name: pytest-spec
Version: 5.2.0
Summary: Library pytest-spec is a pytest plugin to display test execution output like a SPECIFICATION.
Author-email: Pawel Chomicki <pawel.chomicki@gmail.com>
License: GPL-2.0-or-later
Project-URL: Documentation, https://pchomik.ovh/docs/pytest-spec/about
Project-URL: Changelog, https://github.com/pchomik/pytest-spec/CHANGES.txt
Project-URL: Repository, https://github.com/pchomik/pytest-spec
Project-URL: Issues, https://github.com/pchomik/pytest-spec/issues
Keywords: pytest,test,unittest,spec
Classifier: Operating System :: MacOS :: MacOS X
Classifier: Operating System :: Microsoft :: Windows
Classifier: Operating System :: POSIX
Classifier: Programming Language :: Python :: 3
Classifier: Programming Language :: Python :: 3 :: Only
Classifier: Programming Language :: Python :: 3.9
Classifier: Programming Language :: Python :: 3.10
Classifier: Programming Language :: Python :: 3.11
Classifier: Programming Language :: Python :: 3.12
Classifier: Programming Language :: Python :: 3.13
Classifier: Topic :: Software Development :: Libraries
Classifier: Topic :: Software Development :: Testing
Classifier: Topic :: Utilities
Requires-Python: >=3.9
License-File: LICENSE.txt
Provides-Extra: test
Requires-Dist: pytest; extra == "test"
Requires-Dist: pytest-describe; extra == "test"
Requires-Dist: mypy; extra == "test"
Dynamic: license-file
